grafana_fastapi/__init__.py
grafana_fastapi/dao/__init__.py
grafana_fastapi/test/__init__.py
grafana_fastapi/test/test.py
grafana_fastapi-0.1.0.dist-info/METADATA
grafana_fastapi-0.1.0.dist-info/WHEEL
grafana_fastapi-0.1.0.dist-info/RECORD
