Metadata-Version: 2.1
Name: grafana-fastapi
Version: 0.1.0
Summary: 
Author: nockchun
Author-email: nockchun@gmail.com
Requires-Python: >=3.10,<4.0
Classifier: Programming Language :: Python :: 3
Classifier: Programming Language :: Python :: 3.10
Classifier: Programming Language :: Python :: 3.11
Requires-Dist: fastapi (>=0.115.5,<0.116.0)
Requires-Dist: uvicorn (>=0.32.1,<0.33.0)
